{"source/main.ptx": ["my-great-book"], "source/frontmatter.ptx": ["frontmatter"], "source/ch-linear-models.ptx": ["ch-linear-models"], "source/sec-math-models.ptx": ["sec-math-models"], "source/sec-aROC.ptx": ["sec-aROC"], "source/sec-linear-models.ptx": ["sec-linear-models"], "source/sec-linear-trends.ptx": ["sec-linear-trends"], "source/sec-piecewise-linear.ptx": ["sec-piecewise-linear"], "source/ch-linear-models-prep.ptx": ["ch-linear-models"], "source/sec-math-models-prep.ptx": ["sec-math-models-prep"], "source/sec-aROC-prep.ptx": ["sec-aROC-prep"], "source/sec-linear-models-prep.ptx": ["sec-linear-models-prep"], "source/sec-linear-trends-prep.ptx": ["sec-linear-trends-prep"], "source/sec-piecewise-linear-prep.ptx": ["sec-piecewise-linear-prep"], "source/ch-exponential-models.ptx": ["ch-exponential-models"], "source/sec-working-with-percentages.ptx": ["sec-working-with-percentages"], "source/sec-relative-change.ptx": ["sec-relative-change"], "source/sec-exponential-models.ptx": ["sec-exponential-models"], "source/sec-log-models.ptx": ["sec-log-models"], "source/sec-exponential-trends.ptx": ["sec-exponential-trends"], "source/sec-apply-exponential.ptx": ["sec-apply-exponential"], "source/ch-exponential-models-prep.ptx": ["ch-exponential-models-prep"], "source/sec-working-with-percentages-prep.ptx": ["sec-working-with-percentages-prep"], "source/sec-relative-change-prep.ptx": ["sec-relative-change-prep"], "source/sec-exponential-models-prep.ptx": ["sec-exponential-models-prep"], "source/sec-log-models-prep.ptx": ["sec-log-models-prep"], "source/sec-exponential-trends-prep.ptx": ["sec-exponential-trends-prep"], "source/sec-apply-exponential-prep.ptx": ["sec-apply-exponential-prep"], "source/ch-other-models.ptx": ["ch-other-models"], "source/sec-multivar-models.ptx": ["sec-multivar-models"], "source/sec-power-models.ptx": ["sec-power-models"], "source/sec-quad-and-polyn.ptx": ["sec-quad-and-polyn"], "source/ch-other-models-prep.ptx": ["ch-other-models-prep"], "source/sec-multivar-models-prep.ptx": ["sec-multivar-models-prep"], "source/sec-power-models-prep.ptx": ["sec-power-models-prep"], "source/sec-quad-and-polyn-prep.ptx": ["sec-quad-and-polyn-prep"], "source/sec-quad-algebra-prep.ptx": ["sec-quad-algebra-prep"], "source/backmatter.ptx": ["backmatter"]}